yurumikuji/__init__.py
yurumikuji/yurumikuji.py
yurumikuji-0.6.1.dist-info/LICENSE
yurumikuji-0.6.1.dist-info/METADATA
yurumikuji-0.6.1.dist-info/WHEEL
yurumikuji-0.6.1.dist-info/top_level.txt
yurumikuji-0.6.1.dist-info/RECORD
