Metadata-Version: 2.1
Name: yurumikuji
Version: 0.6.1
Summary: kamidana(jinja2 cli) slack additonal.
Home-page: https://github.com/srz-zumix/yurumikuji/
Author: srz_zumix
Author-email: zumix.cpp@gmail.com
License: MIT
Keywords: Slack,Jinja2
Platform: any
Classifier: Development Status :: 4 - Beta
Classifier: Topic :: Utilities
Classifier: License :: OSI Approved :: MIT License
Classifier: Programming Language :: Python
Classifier: Programming Language :: Python :: 3.7
Classifier: Programming Language :: Python :: 3.8
Classifier: Programming Language :: Python :: 3.9
License-File: LICENSE
Requires-Dist: jinja2 >=3.1
Requires-Dist: markupsafe
Requires-Dist: kamidana >=0.10
Requires-Dist: slack-sdk
Requires-Dist: python-dotenv
Provides-Extra: test
Requires-Dist: importlib-metadata <8,>=0.12 ; extra == 'test'
Requires-Dist: tox ; extra == 'test'
Requires-Dist: tox-pyenv ; extra == 'test'
Requires-Dist: pytest ; extra == 'test'
